{"scenario": {"name": "dfs_standalone_d0_h50", "defender": {"telemetry": "NoTelemetry", "strategy": "StaticStandalone", "capabilities": {"DeployDecoy": 0, "HoneyService": 0, "RestoreServer": 0, "HoneyCredentials": 50}}, "attacker": {"name": "DFSAttacker"}, "deployment_instance": {"name": "EquifaxInstance"}}, "experiment_time": 1596.1562087535858, "execution_time": 1166.3627638816833, "setup_time": 429.79344487190247, "flags_captured": [], "data_exfiltrated": [{"name": "data1.json", "time_exfiltrated": 445.814311504364}, {"name": "data2.json", "time_exfiltrated": 651.814311504364}], "hosts_infected": ["attacker", "webserver-a", "webserver-b", "webserver-c", "employee-a", "database-a", "database-b", "employee-b"], "operation_id": "84e30e48-db30-4262-ac1d-1e616f8e75a8", "defender_action_counts": {"shutdown_server": 0, "start_honey_service": 0, "deploy_decoy": 0, "restore_server": 0, "AddHoneyCredentials": 50}}