{"scenario": {"name": "persistentdfs_standalone_d10_h0", "defender": {"telemetry": "NoTelemetry", "strategy": "StaticStandalone", "capabilities": {"DeployDecoy": 10, "HoneyService": 0, "RestoreServer": 0, "HoneyCredentials": 0}}, "attacker": {"name": "persistent_dfs_planner"}, "deployment_instance": {"name": "RingEnvironment"}}, "experiment_time": 2078.614175081253, "execution_time": 1829.7920622825623, "setup_time": 248.8221127986908, "flags_captured": [], "data_exfiltrated": [{"name": "data_host_19.json", "time_exfiltrated": 121.44915866851807}, {"name": "data_host_15.json", "time_exfiltrated": 577.4491586685181}, {"name": "data_host_16.json", "time_exfiltrated": 629.4491586685181}, {"name": "data_host_4.json", "time_exfiltrated": 677.4491586685181}, {"name": "data_host_8.json", "time_exfiltrated": 734.4491586685181}, {"name": "data_host_24.json", "time_exfiltrated": 786.4491586685181}, {"name": "data_host_17.json", "time_exfiltrated": 848.4491586685181}, {"name": "data_host_14.json", "time_exfiltrated": 890.4491586685181}, {"name": "data_host_21.json", "time_exfiltrated": 943.4491586685181}, {"name": "data_host_13.json", "time_exfiltrated": 990.4491586685181}, {"name": "data_host_3.json", "time_exfiltrated": 1037.449158668518}, {"name": "data_host_22.json", "time_exfiltrated": 1089.449158668518}, {"name": "data_host_1.json", "time_exfiltrated": 1142.449158668518}, {"name": "data_host_23.json", "time_exfiltrated": 1199.449158668518}, {"name": "data_host_6.json", "time_exfiltrated": 1246.449158668518}, {"name": "data_host_11.json", "time_exfiltrated": 1303.449158668518}, {"name": "data_host_0.json", "time_exfiltrated": 1365.449158668518}, {"name": "data_host_10.json", "time_exfiltrated": 1413.449158668518}, {"name": "data_host_9.json", "time_exfiltrated": 1460.449158668518}, {"name": "data_host_20.json", "time_exfiltrated": 1512.449158668518}, {"name": "data_host_7.json", "time_exfiltrated": 1569.449158668518}, {"name": "data_host_18.json", "time_exfiltrated": 1622.449158668518}, {"name": "data_host_5.json", "time_exfiltrated": 1674.449158668518}, {"name": "data_host_12.json", "time_exfiltrated": 1726.449158668518}, {"name": "data_host_2.json", "time_exfiltrated": 1768.449158668518}], "hosts_infected": [{"name": "decoy-9", "time_infected": 159.53562474250793}, {"name": "decoy-4", "time_infected": 206.62366032600403}, {"name": "decoy-6", "time_infected": 248.70926713943481}, {"name": "decoy-1", "time_infected": 290.77042174339294}, {"name": "decoy-0", "time_infected": 322.857230424881}, {"name": "decoy-5", "time_infected": 359.92026114463806}, {"name": "decoy-7", "time_infected": 392.00807189941406}, {"name": "decoy-8", "time_infected": 434.09126710891724}, {"name": "decoy-3", "time_infected": 471.1814589500427}, {"name": "decoy-2", "time_infected": 508.30222368240356}, {"name": "host-15", "time_infected": 535.8609175682068}, {"name": "host-16", "time_infected": 593.1333525180817}, {"name": "host-4", "time_infected": 645.3610141277313}, {"name": "host-8", "time_infected": 692.5414097309113}, {"name": "host-24", "time_infected": 749.7659208774567}, {"name": "host-17", "time_infected": 811.9414393901825}, {"name": "host-14", "time_infected": 859.1574473381042}, {"name": "host-21", "time_infected": 906.3638982772827}, {"name": "host-13", "time_infected": 958.5880060195923}, {"name": "host-3", "time_infected": 1005.835057258606}, {"name": "host-22", "time_infected": 1048.048800945282}, {"name": "host-1", "time_infected": 1110.2822773456573}, {"name": "host-23", "time_infected": 1157.526883840561}, {"name": "host-6", "time_infected": 1214.7525608539581}, {"name": "host-11", "time_infected": 1261.96870470047}, {"name": "host-0", "time_infected": 1324.193391084671}, {"name": "host-10", "time_infected": 1381.4164662361145}, {"name": "host-9", "time_infected": 1423.6339333057404}, {"name": "host-20", "time_infected": 1480.8431668281555}, {"name": "host-7", "time_infected": 1528.0982611179352}, {"name": "host-18", "time_infected": 1585.3406691551208}, {"name": "host-5", "time_infected": 1637.5880210399628}, {"name": "host-12", "time_infected": 1684.835886001587}, {"name": "host-2", "time_infected": 1737.0389294624329}, {"name": "host-19", "time_infected": 1784.2938268184662}], "operation_id": "2024-11-06_11-03-18", "defender_action_counts": {"shutdown_server": 0, "start_honey_service": 0, "deploy_decoy": 10, "restore_server": 0, "AddHoneyCredentials": 0}}