{"scenario": {"name": "baseline_standalone_d4_h0", "defender": {"telemetry": "NoTelemetry", "strategy": "StaticStandalone", "capabilities": {"DeployDecoy": 4, "HoneyService": 0, "RestoreServer": 0, "HoneyCredentials": 0}}, "attacker": {"name": "EquifaxBaselineAttacker"}, "deployment_instance": {"name": "EquifaxLarge"}}, "experiment_time": 2797.816757917404, "execution_time": 2515.600362300873, "setup_time": 282.2163956165314, "flags_captured": [], "data_exfiltrated": [{"name": "data_database_21.json", "time_exfiltrated": 230.07478833198547}, {"name": "data_database_2.json", "time_exfiltrated": 278.0747883319855}, {"name": "data_database_0.json", "time_exfiltrated": 330.0747883319855}, {"name": "data_database_40.json", "time_exfiltrated": 377.0747883319855}, {"name": "data_database_32.json", "time_exfiltrated": 415.0747883319855}, {"name": "data_database_14.json", "time_exfiltrated": 457.0747883319855}, {"name": "data_database_23.json", "time_exfiltrated": 509.0747883319855}, {"name": "data_database_17.json", "time_exfiltrated": 556.0747883319855}, {"name": "data_database_16.json", "time_exfiltrated": 599.0747883319855}, {"name": "data_database_45.json", "time_exfiltrated": 656.0747883319855}, {"name": "data_database_12.json", "time_exfiltrated": 703.0747883319855}, {"name": "data_database_19.json", "time_exfiltrated": 751.0747883319855}, {"name": "data_database_36.json", "time_exfiltrated": 798.0747883319855}, {"name": "data_database_41.json", "time_exfiltrated": 845.0747883319855}, {"name": "data_database_6.json", "time_exfiltrated": 903.0747883319855}, {"name": "data_database_35.json", "time_exfiltrated": 950.0747883319855}, {"name": "data_database_33.json", "time_exfiltrated": 1007.0747883319855}, {"name": "data_database_26.json", "time_exfiltrated": 1065.0747883319855}, {"name": "data_database_24.json", "time_exfiltrated": 1112.0747883319855}, {"name": "data_database_7.json", "time_exfiltrated": 1165.0747883319855}, {"name": "data_database_10.json", "time_exfiltrated": 1212.0747883319855}, {"name": "data_database_47.json", "time_exfiltrated": 1250.0747883319855}, {"name": "data_database_46.json", "time_exfiltrated": 1297.0747883319855}, {"name": "data_database_38.json", "time_exfiltrated": 1339.0747883319855}, {"name": "data_database_29.json", "time_exfiltrated": 1382.0747883319855}, {"name": "data_database_44.json", "time_exfiltrated": 1424.0747883319855}, {"name": "data_database_15.json", "time_exfiltrated": 1483.0747883319855}, {"name": "data_database_20.json", "time_exfiltrated": 1526.0747883319855}, {"name": "data_database_1.json", "time_exfiltrated": 1569.0747883319855}, {"name": "data_database_28.json", "time_exfiltrated": 1617.0747883319855}, {"name": "data_database_27.json", "time_exfiltrated": 1664.0747883319855}, {"name": "data_database_13.json", "time_exfiltrated": 1708.0747883319855}, {"name": "data_database_5.json", "time_exfiltrated": 1766.0747883319855}, {"name": "data_database_22.json", "time_exfiltrated": 1814.0747883319855}, {"name": "data_database_37.json", "time_exfiltrated": 1856.0747883319855}, {"name": "data_database_3.json", "time_exfiltrated": 1904.0747883319855}, {"name": "data_database_25.json", "time_exfiltrated": 1951.0747883319855}, {"name": "data_database_4.json", "time_exfiltrated": 2000.0747883319855}, {"name": "data_database_11.json", "time_exfiltrated": 2047.0747883319855}, {"name": "data_database_39.json", "time_exfiltrated": 2132.0747883319855}, {"name": "data_database_34.json", "time_exfiltrated": 2132.0747883319855}, {"name": "data_database_43.json", "time_exfiltrated": 2175.0747883319855}, {"name": "data_database_30.json", "time_exfiltrated": 2233.0747883319855}, {"name": "data_database_42.json", "time_exfiltrated": 2280.0747883319855}, {"name": "data_database_31.json", "time_exfiltrated": 2364.0747883319855}, {"name": "data_database_9.json", "time_exfiltrated": 2364.0747883319855}, {"name": "data_database_8.json", "time_exfiltrated": 2403.0747883319855}, {"name": "data_database_18.json", "time_exfiltrated": 2451.0747883319855}], "hosts_infected": ["attacker", "decoy-2", "decoy-1", "webserver-1", "webserver-0", "database-21", "database-2", "database-0", "database-40", "database-32", "database-14", "database-23", "database-17", "database-16", "database-45", "database-12", "database-19", "database-36", "database-41", "database-6", "database-35", "database-33", "database-26", "database-24", "database-7", "database-10", "database-47", "database-46", "database-38", "database-29", "database-44", "database-15", "database-20", "database-1", "database-28", "database-27", "database-13", "database-5", "database-22", "database-37", "database-3", "database-25", "database-4", "database-11", "database-39", "database-34", "database-43", "database-30", "database-42", "database-31", "database-9", "database-8", "database-18", "decoy-3", "decoy-0"], "operation_id": "a5af2e55-78f0-49ee-9cbd-e0641fe7e5cd", "defender_action_counts": {"shutdown_server": 0, "start_honey_service": 0, "deploy_decoy": 4, "restore_server": 0, "AddHoneyCredentials": 0}}