{"scenario": {"name": "baseline_layered_d10_h50", "defender": {"telemetry": "NoTelemetry", "strategy": "StaticLayered", "capabilities": {"DeployDecoy": 10, "HoneyService": 0, "RestoreServer": 0, "HoneyCredentials": 50}}, "attacker": {"name": "EquifaxBaselineAttacker"}, "deployment_instance": {"name": "EquifaxLarge"}}, "experiment_time": 4737.763793468475, "execution_time": 3408.013646841049, "setup_time": 1329.7501466274261, "flags_captured": [], "data_exfiltrated": [{"name": "data_database_19.json", "time_exfiltrated": 713.873366355896}, {"name": "data_database_16.json", "time_exfiltrated": 849.873366355896}, {"name": "data_database_32.json", "time_exfiltrated": 920.873366355896}, {"name": "data_database_8.json", "time_exfiltrated": 965.873366355896}, {"name": "data_database_37.json", "time_exfiltrated": 1016.873366355896}, {"name": "data_database_25.json", "time_exfiltrated": 1066.873366355896}, {"name": "data_database_45.json", "time_exfiltrated": 1157.873366355896}, {"name": "data_database_31.json", "time_exfiltrated": 1207.873366355896}, {"name": "data_database_30.json", "time_exfiltrated": 1258.873366355896}, {"name": "data_database_23.json", "time_exfiltrated": 1298.873366355896}, {"name": "data_database_46.json", "time_exfiltrated": 1348.873366355896}, {"name": "data_database_24.json", "time_exfiltrated": 1440.873366355896}, {"name": "data_database_40.json", "time_exfiltrated": 1480.873366355896}, {"name": "data_database_39.json", "time_exfiltrated": 1521.873366355896}, {"name": "data_database_28.json", "time_exfiltrated": 1644.873366355896}, {"name": "data_database_14.json", "time_exfiltrated": 1690.873366355896}, {"name": "data_database_34.json", "time_exfiltrated": 1732.873366355896}, {"name": "data_database_12.json", "time_exfiltrated": 1773.873366355896}, {"name": "data_database_42.json", "time_exfiltrated": 1825.873366355896}, {"name": "data_database_43.json", "time_exfiltrated": 1866.873366355896}, {"name": "data_database_33.json", "time_exfiltrated": 1942.873366355896}, {"name": "data_database_2.json", "time_exfiltrated": 1988.873366355896}, {"name": "data_database_44.json", "time_exfiltrated": 2038.873366355896}, {"name": "data_database_41.json", "time_exfiltrated": 2089.873366355896}, {"name": "data_database_27.json", "time_exfiltrated": 2175.873366355896}, {"name": "data_database_22.json", "time_exfiltrated": 2225.873366355896}, {"name": "data_database_47.json", "time_exfiltrated": 2266.873366355896}, {"name": "data_database_29.json", "time_exfiltrated": 2302.873366355896}, {"name": "data_database_4.json", "time_exfiltrated": 2342.873366355896}, {"name": "data_database_3.json", "time_exfiltrated": 2384.873366355896}, {"name": "data_database_11.json", "time_exfiltrated": 2480.873366355896}, {"name": "data_database_17.json", "time_exfiltrated": 2521.873366355896}, {"name": "data_database_10.json", "time_exfiltrated": 2567.873366355896}, {"name": "data_database_9.json", "time_exfiltrated": 2607.873366355896}, {"name": "data_database_18.json", "time_exfiltrated": 2643.873366355896}, {"name": "data_database_13.json", "time_exfiltrated": 2765.873366355896}, {"name": "data_database_0.json", "time_exfiltrated": 2816.873366355896}, {"name": "data_database_38.json", "time_exfiltrated": 2861.873366355896}, {"name": "data_database_15.json", "time_exfiltrated": 2902.873366355896}, {"name": "data_database_1.json", "time_exfiltrated": 2943.873366355896}, {"name": "data_database_26.json", "time_exfiltrated": 3032.873366355896}, {"name": "data_database_6.json", "time_exfiltrated": 3075.873366355896}, {"name": "data_database_7.json", "time_exfiltrated": 3169.873366355896}, {"name": "data_database_20.json", "time_exfiltrated": 3169.873366355896}, {"name": "data_database_5.json", "time_exfiltrated": 3263.873366355896}, {"name": "data_database_36.json", "time_exfiltrated": 3304.873366355896}, {"name": "data_database_21.json", "time_exfiltrated": 3355.873366355896}, {"name": "data_database_35.json", "time_exfiltrated": 3401.873366355896}], "hosts_infected": ["attacker", "decoy-6", "decoy-1", "webserver-1", "decoy-4", "decoy-7", "decoy-8", "decoy-0", "decoy-9", "webserver-0", "database-19", "database-16", "database-32", "database-8", "database-37", "database-25", "database-45", "database-31", "database-30", "database-23", "database-46", "decoy-3", "database-24", "database-40", "database-39", "database-28", "database-14", "database-34", "database-12", "database-42", "database-43", "decoy-2", "database-33", "database-2", "database-44", "database-41", "database-27", "database-22", "database-47", "database-29", "database-4", "database-3", "database-11", "database-17", "database-10", "database-9", "database-18", "database-13", "database-0", "database-38", "database-15", "database-1", "database-26", "database-6", "database-7", "database-20", "database-5", "database-36", "database-21", "database-35"], "operation_id": "67a888c4-2844-466b-ab74-43f8440323e2", "defender_action_counts": {"shutdown_server": 0, "start_honey_service": 0, "deploy_decoy": 10, "restore_server": 0, "AddHoneyCredentials": 0}}