{"scenario": {"name": "darkside_standalone_d10_h0", "defender": {"telemetry": "NoTelemetry", "strategy": "StaticStandalone", "capabilities": {"DeployDecoy": 10, "HoneyService": 0, "RestoreServer": 0, "HoneyCredentials": 0}}, "attacker": {"name": "darkside"}, "deployment_instance": {"name": "ICSEnvironment"}}, "experiment_time": 1361.7237422466278, "execution_time": 959.0849652290344, "setup_time": 402.6387770175934, "flags_captured": [], "data_exfiltrated": [], "hosts_infected": [{"name": "decoy-9", "time_infected": 97.23455381393433}, {"name": "decoy-5", "time_infected": 129.3172755241394}, {"name": "manage-b-0", "time_infected": 154.34671258926392}, {"name": "decoy-3", "time_infected": 174.37405729293823}, {"name": "decoy-0", "time_infected": 194.4085807800293}, {"name": "decoy-6", "time_infected": 214.42958903312683}, {"name": "sensor-15", "time_infected": 270.60635352134705}, {"name": "sensor-2", "time_infected": 280.62755942344666}, {"name": "sensor-12", "time_infected": 290.6529643535614}, {"name": "sensor-1", "time_infected": 300.67625522613525}, {"name": "sensor-4", "time_infected": 310.69735741615295}, {"name": "sensor-18", "time_infected": 325.72337913513184}, {"name": "sensor-3", "time_infected": 335.7498309612274}, {"name": "sensor-5", "time_infected": 350.7677438259125}, {"name": "sensor-6", "time_infected": 360.79611349105835}, {"name": "sensor-13", "time_infected": 375.8426377773285}, {"name": "sensor-10", "time_infected": 385.8593771457672}, {"name": "sensor-17", "time_infected": 400.8775472640991}, {"name": "sensor-7", "time_infected": 410.8946542739868}, {"name": "sensor-14", "time_infected": 425.913635969162}, {"name": "sensor-19", "time_infected": 435.93062806129456}, {"name": "sensor-9", "time_infected": 445.94863200187683}, {"name": "sensor-0", "time_infected": 455.96512961387634}, {"name": "sensor-16", "time_infected": 465.98246002197266}, {"name": "sensor-11", "time_infected": 476.00054836273193}, {"name": "sensor-8", "time_infected": 491.01820135116577}, {"name": "control-host-2", "time_infected": 564.1759161949158}, {"name": "control-host-1", "time_infected": 724.6060779094696}, {"name": "control-host-0", "time_infected": 763.698801279068}, {"name": "control-host-3", "time_infected": 807.7953791618347}, {"name": "control-host-4", "time_infected": 829.8484582901001}], "operation_id": "2024-11-08_02-18-13", "defender_action_counts": {"shutdown_server": 0, "start_honey_service": 0, "deploy_decoy": 10, "restore_server": 0, "AddHoneyCredentials": 0}}