{"scenario": {"name": "targeted_standalone_d10_h50", "defender": {"telemetry": "NoTelemetry", "strategy": "StaticStandalone", "capabilities": {"DeployDecoy": 10, "HoneyService": 0, "RestoreServer": 0, "HoneyCredentials": 50}}, "attacker": {"name": "targeted"}, "deployment_instance": {"name": "EquifaxLarge"}}, "experiment_time": 4061.660187959671, "execution_time": 3072.8377187252045, "setup_time": 988.8224692344666, "flags_captured": [], "data_exfiltrated": [{"name": "data_database_45.json", "time_exfiltrated": 305.72680282592773}, {"name": "data_database_2.json", "time_exfiltrated": 357.72680282592773}, {"name": "data_database_31.json", "time_exfiltrated": 409.72680282592773}, {"name": "data_database_25.json", "time_exfiltrated": 462.72680282592773}, {"name": "data_database_39.json", "time_exfiltrated": 504.72680282592773}, {"name": "data_database_41.json", "time_exfiltrated": 547.7268028259277}, {"name": "data_database_9.json", "time_exfiltrated": 594.7268028259277}, {"name": "data_database_33.json", "time_exfiltrated": 632.7268028259277}, {"name": "data_database_32.json", "time_exfiltrated": 674.7268028259277}, {"name": "data_database_20.json", "time_exfiltrated": 711.7268028259277}, {"name": "data_database_5.json", "time_exfiltrated": 754.7268028259277}, {"name": "data_database_14.json", "time_exfiltrated": 811.7268028259277}, {"name": "data_database_46.json", "time_exfiltrated": 869.7268028259277}, {"name": "data_database_37.json", "time_exfiltrated": 931.7268028259277}, {"name": "data_database_24.json", "time_exfiltrated": 989.7268028259277}, {"name": "data_database_12.json", "time_exfiltrated": 1036.7268028259277}, {"name": "data_database_22.json", "time_exfiltrated": 1099.7268028259277}, {"name": "data_database_40.json", "time_exfiltrated": 1156.7268028259277}, {"name": "data_database_13.json", "time_exfiltrated": 1219.7268028259277}, {"name": "data_database_47.json", "time_exfiltrated": 1266.7268028259277}, {"name": "data_database_26.json", "time_exfiltrated": 1319.7268028259277}, {"name": "data_database_35.json", "time_exfiltrated": 1356.7268028259277}, {"name": "data_database_27.json", "time_exfiltrated": 1398.7268028259277}, {"name": "data_database_36.json", "time_exfiltrated": 1446.7268028259277}, {"name": "data_database_0.json", "time_exfiltrated": 1493.7268028259277}, {"name": "data_database_44.json", "time_exfiltrated": 1541.7268028259277}, {"name": "data_database_21.json", "time_exfiltrated": 1583.7268028259277}, {"name": "data_database_16.json", "time_exfiltrated": 1631.7268028259277}, {"name": "data_database_10.json", "time_exfiltrated": 1683.7268028259277}, {"name": "data_database_42.json", "time_exfiltrated": 1720.7268028259277}, {"name": "data_database_11.json", "time_exfiltrated": 1773.7268028259277}, {"name": "data_database_17.json", "time_exfiltrated": 1836.7268028259277}, {"name": "data_database_3.json", "time_exfiltrated": 1883.7268028259277}, {"name": "data_database_8.json", "time_exfiltrated": 1956.7268028259277}, {"name": "data_database_29.json", "time_exfiltrated": 2003.7268028259277}, {"name": "data_database_6.json", "time_exfiltrated": 2051.7268028259277}, {"name": "data_database_7.json", "time_exfiltrated": 2109.7268028259277}, {"name": "data_database_43.json", "time_exfiltrated": 2167.7268028259277}, {"name": "data_database_15.json", "time_exfiltrated": 2219.7268028259277}, {"name": "data_database_34.json", "time_exfiltrated": 2262.7268028259277}, {"name": "data_database_28.json", "time_exfiltrated": 2304.7268028259277}, {"name": "data_database_30.json", "time_exfiltrated": 2346.7268028259277}, {"name": "data_database_23.json", "time_exfiltrated": 2399.7268028259277}, {"name": "data_database_19.json", "time_exfiltrated": 2457.7268028259277}, {"name": "data_database_1.json", "time_exfiltrated": 2504.7268028259277}, {"name": "data_database_38.json", "time_exfiltrated": 2541.7268028259277}, {"name": "data_database_18.json", "time_exfiltrated": 2589.7268028259277}, {"name": "data_database_4.json", "time_exfiltrated": 2636.7268028259277}], "hosts_infected": [{"name": "decoy-8", "time_infected": 65.39955067634583}, {"name": "webserver-1", "time_infected": 80.46202659606934}, {"name": "decoy-6", "time_infected": 112.64541816711426}, {"name": "decoy-5", "time_infected": 144.82292294502258}, {"name": "webserver-0", "time_infected": 194.04524397850037}, {"name": "decoy-7", "time_infected": 209.10912561416626}, {"name": "database-45", "time_infected": 246.2952811717987}, {"name": "database-2", "time_infected": 315.8258376121521}, {"name": "database-31", "time_infected": 368.21954321861267}, {"name": "database-25", "time_infected": 425.64741039276123}, {"name": "database-39", "time_infected": 435.7121353149414}, {"name": "database-41", "time_infected": 478.14715600013733}, {"name": "database-9", "time_infected": 515.5297210216522}, {"name": "database-33", "time_infected": 563.2340235710144}, {"name": "database-32", "time_infected": 605.6069855690002}, {"name": "database-20", "time_infected": 642.9480328559875}, {"name": "database-5", "time_infected": 685.2936401367188}, {"name": "database-14", "time_infected": 765.0975677967072}, {"name": "database-46", "time_infected": 832.6775295734406}, {"name": "database-37", "time_infected": 890.1063556671143}, {"name": "database-24", "time_infected": 942.5106270313263}, {"name": "database-12", "time_infected": 999.9322731494904}, {"name": "database-22", "time_infected": 1047.5568964481354}, {"name": "database-40", "time_infected": 1109.9915299415588}, {"name": "database-13", "time_infected": 1172.5914266109467}, {"name": "database-47", "time_infected": 1182.659569978714}, {"name": "database-26", "time_infected": 1277.399334192276}, {"name": "database-35", "time_infected": 1287.465307712555}, {"name": "database-27", "time_infected": 1329.8181536197662}, {"name": "database-36", "time_infected": 1367.12100481987}, {"name": "database-0", "time_infected": 1457.1104805469513}, {"name": "database-44", "time_infected": 1467.1447179317474}, {"name": "database-21", "time_infected": 1509.7880945205688}, {"name": "database-16", "time_infected": 1552.1204001903534}, {"name": "database-10", "time_infected": 1599.4770545959473}, {"name": "database-42", "time_infected": 1646.8028573989868}, {"name": "database-11", "time_infected": 1731.6202397346497}, {"name": "database-17", "time_infected": 1789.0190515518188}, {"name": "database-3", "time_infected": 1799.06289935112}, {"name": "database-8", "time_infected": 1914.486222743988}, {"name": "database-29", "time_infected": 1924.5132050514221}, {"name": "database-6", "time_infected": 1972.1702451705933}, {"name": "database-7", "time_infected": 2067.1480457782745}, {"name": "database-43", "time_infected": 2120.0153427124023}, {"name": "database-15", "time_infected": 2183.0186512470245}, {"name": "database-34", "time_infected": 2193.085894346237}, {"name": "database-28", "time_infected": 2230.522907972336}, {"name": "database-30", "time_infected": 2272.8491406440735}, {"name": "database-23", "time_infected": 2357.7004051208496}, {"name": "database-19", "time_infected": 2415.152317047119}, {"name": "database-1", "time_infected": 2425.2213921546936}, {"name": "database-38", "time_infected": 2472.9465153217316}, {"name": "database-18", "time_infected": 2515.293359041214}, {"name": "database-4", "time_infected": 2557.618588209152}, {"name": "decoy-0", "time_infected": 2891.3001656532288}, {"name": "decoy-9", "time_infected": 2918.491048812866}, {"name": "decoy-2", "time_infected": 2933.568564891815}, {"name": "decoy-4", "time_infected": 2982.8966619968414}, {"name": "decoy-3", "time_infected": 3020.115560531616}, {"name": "decoy-1", "time_infected": 3052.5454564094543}], "operation_id": "2024-11-08_10-56-36", "defender_action_counts": {"shutdown_server": 0, "start_honey_service": 0, "deploy_decoy": 10, "restore_server": 0, "AddHoneyCredentials": 0}}