{"scenario": {"name": "persistentdfs_standalone_d10_h50", "defender": {"telemetry": "NoTelemetry", "strategy": "StaticStandalone", "capabilities": {"DeployDecoy": 10, "HoneyService": 0, "RestoreServer": 0, "HoneyCredentials": 50}}, "attacker": {"name": "persistent_dfs_planner"}, "deployment_instance": {"name": "RingEnvironment"}}, "experiment_time": 2610.500403881073, "execution_time": 2297.375210046768, "setup_time": 313.1251938343048, "flags_captured": [], "data_exfiltrated": [{"name": "data_host_11.json", "time_exfiltrated": 126.8805181980133}, {"name": "data_host_0.json", "time_exfiltrated": 587.8805181980133}, {"name": "data_host_10.json", "time_exfiltrated": 669.8805181980133}, {"name": "data_host_9.json", "time_exfiltrated": 736.8805181980133}, {"name": "data_host_20.json", "time_exfiltrated": 788.8805181980133}, {"name": "data_host_7.json", "time_exfiltrated": 896.8805181980133}, {"name": "data_host_18.json", "time_exfiltrated": 963.8805181980133}, {"name": "data_host_5.json", "time_exfiltrated": 1056.8805181980133}, {"name": "data_host_12.json", "time_exfiltrated": 1123.8805181980133}, {"name": "data_host_2.json", "time_exfiltrated": 1170.8805181980133}, {"name": "data_host_19.json", "time_exfiltrated": 1222.8805181980133}, {"name": "data_host_15.json", "time_exfiltrated": 1315.8805181980133}, {"name": "data_host_16.json", "time_exfiltrated": 1367.8805181980133}, {"name": "data_host_4.json", "time_exfiltrated": 1424.8805181980133}, {"name": "data_host_8.json", "time_exfiltrated": 1496.8805181980133}, {"name": "data_host_24.json", "time_exfiltrated": 1544.8805181980133}, {"name": "data_host_17.json", "time_exfiltrated": 1601.8805181980133}, {"name": "data_host_14.json", "time_exfiltrated": 1668.8805181980133}, {"name": "data_host_21.json", "time_exfiltrated": 1726.8805181980133}, {"name": "data_host_13.json", "time_exfiltrated": 1773.8805181980133}, {"name": "data_host_3.json", "time_exfiltrated": 1840.8805181980133}, {"name": "data_host_22.json", "time_exfiltrated": 1903.8805181980133}, {"name": "data_host_1.json", "time_exfiltrated": 1945.8805181980133}, {"name": "data_host_23.json", "time_exfiltrated": 2027.8805181980133}, {"name": "data_host_6.json", "time_exfiltrated": 2070.8805181980133}], "hosts_infected": [{"name": "decoy-9", "time_infected": 169.51964688301086}, {"name": "decoy-8", "time_infected": 216.60048294067383}, {"name": "decoy-3", "time_infected": 253.71154928207397}, {"name": "decoy-6", "time_infected": 290.79578971862793}, {"name": "decoy-0", "time_infected": 327.88163924217224}, {"name": "decoy-5", "time_infected": 359.9778492450714}, {"name": "decoy-2", "time_infected": 402.07229685783386}, {"name": "decoy-7", "time_infected": 439.1710991859436}, {"name": "decoy-1", "time_infected": 476.26838064193726}, {"name": "decoy-4", "time_infected": 513.3811466693878}, {"name": "host-0", "time_infected": 550.9447524547577}, {"name": "host-10", "time_infected": 628.210755109787}, {"name": "host-9", "time_infected": 700.4325528144836}, {"name": "host-20", "time_infected": 757.6860918998718}, {"name": "host-7", "time_infected": 860.1028454303741}, {"name": "host-18", "time_infected": 922.3686435222626}, {"name": "host-5", "time_infected": 1019.757707118988}, {"name": "host-12", "time_infected": 1082.021460056305}, {"name": "host-2", "time_infected": 1134.2274837493896}, {"name": "host-19", "time_infected": 1191.491660118103}, {"name": "host-15", "time_infected": 1273.8359127044678}, {"name": "host-16", "time_infected": 1331.0618464946747}, {"name": "host-4", "time_infected": 1393.3434579372406}, {"name": "host-8", "time_infected": 1460.6437735557556}, {"name": "host-24", "time_infected": 1507.9099056720734}, {"name": "host-17", "time_infected": 1560.1275284290314}, {"name": "host-14", "time_infected": 1632.6046314239502}, {"name": "host-21", "time_infected": 1690.0184879302979}, {"name": "host-13", "time_infected": 1737.2435574531555}, {"name": "host-3", "time_infected": 1799.4901804924011}, {"name": "host-22", "time_infected": 1866.7711288928986}, {"name": "host-1", "time_infected": 1913.9705820083618}, {"name": "host-23", "time_infected": 1991.6364958286285}, {"name": "host-6", "time_infected": 2038.8595175743103}, {"name": "host-11", "time_infected": 2086.234360218048}], "operation_id": "2024-11-07_00-28-20", "defender_action_counts": {"shutdown_server": 0, "start_honey_service": 0, "deploy_decoy": 10, "restore_server": 0, "AddHoneyCredentials": 0}}