{"scenario": {"name": "targeted_advancedReactive_d10_d0", "defender": {"telemetry": "ReactiveCredentials", "strategy": "ReactiveStandalone", "capabilities": {"DeployDecoy": 10, "HoneyService": 0, "RestoreServer": 0, "HoneyCredentials": 0}}, "attacker": {"name": "targeted"}, "deployment_instance": {"name": "EquifaxLarge"}}, "experiment_time": 3300.8865480422974, "execution_time": 2368.8331899642944, "setup_time": 932.0533580780029, "flags_captured": [], "data_exfiltrated": [{"name": "data_database_15.json", "time_exfiltrated": 277.57545471191406}, {"name": "data_database_1.json", "time_exfiltrated": 315.57545471191406}, {"name": "data_database_41.json", "time_exfiltrated": 362.57545471191406}, {"name": "data_database_0.json", "time_exfiltrated": 404.57545471191406}, {"name": "data_database_4.json", "time_exfiltrated": 452.57545471191406}, {"name": "data_database_33.json", "time_exfiltrated": 499.57545471191406}, {"name": "data_database_18.json", "time_exfiltrated": 537.5754547119141}, {"name": "data_database_40.json", "time_exfiltrated": 579.5754547119141}, {"name": "data_database_42.json", "time_exfiltrated": 621.5754547119141}, {"name": "data_database_2.json", "time_exfiltrated": 664.5754547119141}, {"name": "data_database_37.json", "time_exfiltrated": 701.5754547119141}, {"name": "data_database_3.json", "time_exfiltrated": 749.5754547119141}, {"name": "data_database_10.json", "time_exfiltrated": 801.5754547119141}, {"name": "data_database_21.json", "time_exfiltrated": 848.5754547119141}, {"name": "data_database_17.json", "time_exfiltrated": 886.5754547119141}, {"name": "data_database_5.json", "time_exfiltrated": 928.5754547119141}, {"name": "data_database_22.json", "time_exfiltrated": 971.5754547119141}, {"name": "data_database_11.json", "time_exfiltrated": 1013.5754547119141}, {"name": "data_database_44.json", "time_exfiltrated": 1050.575454711914}, {"name": "data_database_26.json", "time_exfiltrated": 1088.575454711914}, {"name": "data_database_6.json", "time_exfiltrated": 1130.575454711914}, {"name": "data_database_14.json", "time_exfiltrated": 1172.575454711914}, {"name": "data_database_38.json", "time_exfiltrated": 1215.575454711914}, {"name": "data_database_12.json", "time_exfiltrated": 1257.575454711914}, {"name": "data_database_25.json", "time_exfiltrated": 1300.575454711914}, {"name": "data_database_43.json", "time_exfiltrated": 1342.575454711914}, {"name": "data_database_45.json", "time_exfiltrated": 1380.575454711914}, {"name": "data_database_39.json", "time_exfiltrated": 1422.575454711914}, {"name": "data_database_13.json", "time_exfiltrated": 1465.575454711914}, {"name": "data_database_47.json", "time_exfiltrated": 1502.575454711914}, {"name": "data_database_46.json", "time_exfiltrated": 1545.575454711914}, {"name": "data_database_8.json", "time_exfiltrated": 1592.575454711914}, {"name": "data_database_19.json", "time_exfiltrated": 1640.575454711914}, {"name": "data_database_28.json", "time_exfiltrated": 1682.575454711914}, {"name": "data_database_35.json", "time_exfiltrated": 1730.575454711914}, {"name": "data_database_20.json", "time_exfiltrated": 1777.575454711914}, {"name": "data_database_9.json", "time_exfiltrated": 1830.575454711914}, {"name": "data_database_31.json", "time_exfiltrated": 1872.575454711914}, {"name": "data_database_16.json", "time_exfiltrated": 1920.575454711914}, {"name": "data_database_7.json", "time_exfiltrated": 1962.575454711914}, {"name": "data_database_29.json", "time_exfiltrated": 2010.575454711914}, {"name": "data_database_34.json", "time_exfiltrated": 2052.575454711914}, {"name": "data_database_23.json", "time_exfiltrated": 2095.575454711914}, {"name": "data_database_24.json", "time_exfiltrated": 2142.575454711914}, {"name": "data_database_32.json", "time_exfiltrated": 2190.575454711914}, {"name": "data_database_30.json", "time_exfiltrated": 2228.575454711914}, {"name": "data_database_36.json", "time_exfiltrated": 2275.575454711914}, {"name": "data_database_27.json", "time_exfiltrated": 2308.575454711914}], "hosts_infected": [{"name": "decoy-1", "time_infected": 55.4900643825531}, {"name": "decoy-8", "time_infected": 70.5129280090332}, {"name": "decoy-6", "time_infected": 112.65487718582153}, {"name": "webserver-0", "time_infected": 171.79842615127563}, {"name": "webserver-1", "time_infected": 191.8652606010437}, {"name": "database-15", "time_infected": 219.05261397361755}, {"name": "database-1", "time_infected": 246.21669363975525}, {"name": "database-41", "time_infected": 288.5710356235504}, {"name": "database-0", "time_infected": 330.877774477005}, {"name": "database-4", "time_infected": 373.22483253479004}, {"name": "database-33", "time_infected": 415.54184436798096}, {"name": "database-18", "time_infected": 467.99615812301636}, {"name": "database-40", "time_infected": 510.36522793769836}, {"name": "database-42", "time_infected": 547.7777698040009}, {"name": "database-2", "time_infected": 590.1211473941803}, {"name": "database-37", "time_infected": 632.5416872501373}, {"name": "database-3", "time_infected": 674.8582119941711}, {"name": "database-10", "time_infected": 717.2081391811371}, {"name": "database-21", "time_infected": 764.805858373642}, {"name": "database-17", "time_infected": 817.1559119224548}, {"name": "database-5", "time_infected": 859.5144076347351}, {"name": "database-22", "time_infected": 896.8438994884491}, {"name": "database-11", "time_infected": 944.3205831050873}, {"name": "database-44", "time_infected": 986.6674301624298}, {"name": "database-26", "time_infected": 1024.0118851661682}, {"name": "database-6", "time_infected": 1061.3872458934784}, {"name": "database-14", "time_infected": 1098.7111704349518}, {"name": "database-38", "time_infected": 1141.0631475448608}, {"name": "database-12", "time_infected": 1183.6125650405884}, {"name": "database-25", "time_infected": 1225.9648566246033}, {"name": "database-43", "time_infected": 1268.6183977127075}, {"name": "database-45", "time_infected": 1310.9390218257904}, {"name": "database-39", "time_infected": 1353.4150292873383}, {"name": "database-13", "time_infected": 1390.8975598812103}, {"name": "database-47", "time_infected": 1433.2547097206116}, {"name": "database-46", "time_infected": 1476.0764911174774}, {"name": "database-8", "time_infected": 1513.5774998664856}, {"name": "database-19", "time_infected": 1556.1798684597015}, {"name": "database-28", "time_infected": 1608.5329303741455}, {"name": "database-35", "time_infected": 1651.053073167801}, {"name": "database-20", "time_infected": 1698.6199667453766}, {"name": "database-9", "time_infected": 1745.9814920425415}, {"name": "database-31", "time_infected": 1793.5524475574493}, {"name": "database-16", "time_infected": 1841.1439809799194}, {"name": "database-7", "time_infected": 1888.5006039142609}, {"name": "database-29", "time_infected": 1936.2475950717926}, {"name": "database-34", "time_infected": 1978.603571176529}, {"name": "database-23", "time_infected": 2026.2356176376343}, {"name": "database-24", "time_infected": 2063.625376224518}, {"name": "database-32", "time_infected": 2111.2752120494843}, {"name": "database-30", "time_infected": 2158.607791185379}, {"name": "database-36", "time_infected": 2201.5458278656006}, {"name": "database-27", "time_infected": 2243.9044902324677}, {"name": "decoy-0", "time_infected": 2323.700642824173}], "operation_id": "2024-11-09_10-45-59", "defender_action_counts": {"shutdown_server": 0, "start_honey_service": 0, "deploy_decoy": 10, "restore_server": 8, "AddHoneyCredentials": 0}}