{"scenario": {"name": "persistentdfs_standalone_d10_h50", "defender": {"telemetry": "NoTelemetry", "strategy": "StaticStandalone", "capabilities": {"DeployDecoy": 10, "HoneyService": 0, "RestoreServer": 0, "HoneyCredentials": 50}}, "attacker": {"name": "persistent_dfs_planner"}, "deployment_instance": {"name": "EquifaxLarge"}}, "experiment_time": 4896.574637889862, "execution_time": 4500.398228883743, "setup_time": 396.1764090061188, "flags_captured": [], "data_exfiltrated": [], "hosts_infected": [{"name": "decoy-8", "time_infected": 82.19263124465942}, {"name": "decoy-7", "time_infected": 109.24301242828369}, {"name": "decoy-8", "time_infected": 151.3070900440216}, {"name": "decoy-4", "time_infected": 183.3517518043518}, {"name": "decoy-2", "time_infected": 220.40287494659424}, {"name": "decoy-3", "time_infected": 257.4554831981659}, {"name": "decoy-8", "time_infected": 289.50970101356506}, {"name": "decoy-0", "time_infected": 321.56255555152893}, {"name": "decoy-7", "time_infected": 348.64592146873474}, {"name": "decoy-1", "time_infected": 385.7030544281006}, {"name": "decoy-3", "time_infected": 417.75568079948425}, {"name": "decoy-2", "time_infected": 454.8006172180176}, {"name": "decoy-7", "time_infected": 491.85665369033813}, {"name": "decoy-2", "time_infected": 523.9052357673645}, {"name": "decoy-6", "time_infected": 555.9564883708954}, {"name": "webserver-0", "time_infected": 598.0058560371399}, {"name": "database-16", "time_infected": 625.0670857429504}], "operation_id": "2024-11-03_00-11-01", "defender_action_counts": {"shutdown_server": 0, "start_honey_service": 0, "deploy_decoy": 10, "restore_server": 0, "AddHoneyCredentials": 0}}