{"scenario": {"name": "darkside_reactiveSimple", "defender": {"telemetry": "SimpleTelemetryAnalysis", "strategy": "ReactiveStandalone", "capabilities": {"DeployDecoy": 10, "HoneyService": 0, "RestoreServer": 0, "HoneyCredentials": 0}}, "attacker": {"name": "darkside"}, "deployment_instance": {"name": "EquifaxLarge"}}, "experiment_time": 4549.08220243454, "execution_time": 3438.7477078437805, "setup_time": 1110.3344945907593, "flags_captured": [], "data_exfiltrated": [{"name": "data_database_0.json", "time_exfiltrated": 2668.528556585312}, {"name": "data_database_1.json", "time_exfiltrated": 2683.528556585312}, {"name": "data_database_10.json", "time_exfiltrated": 2698.528556585312}, {"name": "data_database_11.json", "time_exfiltrated": 2713.528556585312}, {"name": "data_database_12.json", "time_exfiltrated": 2728.528556585312}, {"name": "data_database_13.json", "time_exfiltrated": 2744.528556585312}, {"name": "data_database_14.json", "time_exfiltrated": 2764.528556585312}, {"name": "data_database_15.json", "time_exfiltrated": 2779.528556585312}, {"name": "data_database_16.json", "time_exfiltrated": 2794.528556585312}, {"name": "data_database_17.json", "time_exfiltrated": 2809.528556585312}, {"name": "data_database_18.json", "time_exfiltrated": 2825.528556585312}, {"name": "data_database_19.json", "time_exfiltrated": 2840.528556585312}, {"name": "data_database_2.json", "time_exfiltrated": 2855.528556585312}, {"name": "data_database_20.json", "time_exfiltrated": 2870.528556585312}, {"name": "data_database_21.json", "time_exfiltrated": 2886.528556585312}, {"name": "data_database_22.json", "time_exfiltrated": 2901.528556585312}, {"name": "data_database_23.json", "time_exfiltrated": 2916.528556585312}, {"name": "data_database_24.json", "time_exfiltrated": 2936.528556585312}, {"name": "data_database_25.json", "time_exfiltrated": 2952.528556585312}, {"name": "data_database_26.json", "time_exfiltrated": 2967.528556585312}, {"name": "data_database_27.json", "time_exfiltrated": 2982.528556585312}, {"name": "data_database_28.json", "time_exfiltrated": 3002.528556585312}, {"name": "data_database_29.json", "time_exfiltrated": 3017.528556585312}, {"name": "data_database_3.json", "time_exfiltrated": 3032.528556585312}, {"name": "data_database_30.json", "time_exfiltrated": 3053.528556585312}, {"name": "data_database_31.json", "time_exfiltrated": 3068.528556585312}, {"name": "data_database_32.json", "time_exfiltrated": 3083.528556585312}, {"name": "data_database_33.json", "time_exfiltrated": 3099.528556585312}, {"name": "data_database_34.json", "time_exfiltrated": 3114.528556585312}, {"name": "data_database_35.json", "time_exfiltrated": 3130.528556585312}, {"name": "data_database_36.json", "time_exfiltrated": 3150.528556585312}, {"name": "data_database_37.json", "time_exfiltrated": 3170.528556585312}, {"name": "data_database_38.json", "time_exfiltrated": 3190.528556585312}, {"name": "data_database_39.json", "time_exfiltrated": 3205.528556585312}, {"name": "data_database_4.json", "time_exfiltrated": 3221.528556585312}, {"name": "data_database_40.json", "time_exfiltrated": 3241.528556585312}, {"name": "data_database_41.json", "time_exfiltrated": 3256.528556585312}, {"name": "data_database_42.json", "time_exfiltrated": 3271.528556585312}, {"name": "data_database_43.json", "time_exfiltrated": 3286.528556585312}, {"name": "data_database_44.json", "time_exfiltrated": 3302.528556585312}, {"name": "data_database_45.json", "time_exfiltrated": 3322.528556585312}, {"name": "data_database_46.json", "time_exfiltrated": 3337.528556585312}, {"name": "data_database_47.json", "time_exfiltrated": 3353.528556585312}, {"name": "data_database_5.json", "time_exfiltrated": 3373.528556585312}, {"name": "data_database_6.json", "time_exfiltrated": 3388.528556585312}, {"name": "data_database_7.json", "time_exfiltrated": 3403.528556585312}, {"name": "data_database_8.json", "time_exfiltrated": 3418.528556585312}, {"name": "data_database_9.json", "time_exfiltrated": 3433.528556585312}], "hosts_infected": [{"name": "webserver-0", "time_infected": 70.42819118499756}, {"name": "database-18", "time_infected": 107.5638861656189}, {"name": "database-11", "time_infected": 122.63596796989441}, {"name": "database-33", "time_infected": 137.69929766654968}, {"name": "database-8", "time_infected": 157.7613127231598}, {"name": "database-30", "time_infected": 177.8335931301117}, {"name": "database-23", "time_infected": 192.89583349227905}, {"name": "database-37", "time_infected": 207.9583809375763}, {"name": "database-44", "time_infected": 223.02030491828918}, {"name": "database-38", "time_infected": 243.08955454826355}, {"name": "database-25", "time_infected": 258.1549210548401}, {"name": "database-19", "time_infected": 278.222220659256}, {"name": "database-43", "time_infected": 293.2799994945526}, {"name": "database-22", "time_infected": 313.33511996269226}, {"name": "database-10", "time_infected": 328.38461232185364}, {"name": "database-26", "time_infected": 343.4525456428528}, {"name": "database-13", "time_infected": 358.51744532585144}, {"name": "database-6", "time_infected": 373.57927417755127}, {"name": "database-14", "time_infected": 393.64518880844116}, {"name": "database-3", "time_infected": 408.7178752422333}, {"name": "database-40", "time_infected": 423.7558195590973}, {"name": "database-15", "time_infected": 438.81794595718384}, {"name": "database-2", "time_infected": 453.87735772132874}, {"name": "database-42", "time_infected": 473.9420099258423}, {"name": "database-4", "time_infected": 494.00383973121643}, {"name": "database-29", "time_infected": 514.0673372745514}, {"name": "database-20", "time_infected": 529.1242959499359}, {"name": "database-28", "time_infected": 544.1876800060272}, {"name": "database-1", "time_infected": 559.2474594116211}, {"name": "database-47", "time_infected": 569.3182299137115}, {"name": "database-35", "time_infected": 589.3834104537964}, {"name": "database-31", "time_infected": 604.4168438911438}, {"name": "database-24", "time_infected": 624.4818859100342}, {"name": "database-27", "time_infected": 639.5421690940857}, {"name": "database-39", "time_infected": 654.6079142093658}, {"name": "database-46", "time_infected": 669.6682980060577}, {"name": "database-5", "time_infected": 684.7320685386658}, {"name": "database-17", "time_infected": 699.7688562870026}, {"name": "database-7", "time_infected": 714.8347606658936}, {"name": "database-36", "time_infected": 729.9322810173035}, {"name": "database-41", "time_infected": 744.9870924949646}, {"name": "database-12", "time_infected": 760.032416343689}, {"name": "database-45", "time_infected": 775.0954012870789}, {"name": "database-0", "time_infected": 790.1607778072357}, {"name": "database-9", "time_infected": 800.2315413951874}, {"name": "database-32", "time_infected": 815.2971460819244}, {"name": "database-16", "time_infected": 830.3618042469025}, {"name": "database-34", "time_infected": 840.4187800884247}, {"name": "database-21", "time_infected": 850.4819061756134}, {"name": "decoy-1", "time_infected": 882.677960395813}, {"name": "decoy-6", "time_infected": 902.7393124103546}, {"name": "decoy-5", "time_infected": 917.7682409286499}, {"name": "decoy-3", "time_infected": 932.832718372345}, {"name": "webserver-1", "time_infected": 952.8600928783417}], "operation_id": "2024-11-06_06-07-19", "defender_action_counts": {"shutdown_server": 0, "start_honey_service": 0, "deploy_decoy": 10, "restore_server": 8, "AddHoneyCredentials": 0}}