{"scenario": {"name": "persistentdfs_standalone_d0_h0", "defender": {"telemetry": "NoTelemetry", "strategy": "StaticStandalone", "capabilities": {"DeployDecoy": 0, "HoneyService": 0, "RestoreServer": 0, "HoneyCredentials": 0}}, "attacker": {"name": "persistent_dfs_planner"}, "deployment_instance": {"name": "EquifaxLarge"}}, "experiment_time": 2690.8289697170258, "execution_time": 2246.5221059322357, "setup_time": 444.30686378479004, "flags_captured": [], "data_exfiltrated": [{"name": "data_database_9.json", "time_exfiltrated": 178.73564338684082}, {"name": "data_database_27.json", "time_exfiltrated": 220.73564338684082}, {"name": "data_database_32.json", "time_exfiltrated": 263.7356433868408}, {"name": "data_database_47.json", "time_exfiltrated": 305.7356433868408}, {"name": "data_database_5.json", "time_exfiltrated": 357.7356433868408}, {"name": "data_database_30.json", "time_exfiltrated": 400.7356433868408}, {"name": "data_database_44.json", "time_exfiltrated": 437.7356433868408}, {"name": "data_database_42.json", "time_exfiltrated": 484.7356433868408}, {"name": "data_database_10.json", "time_exfiltrated": 537.7356433868408}, {"name": "data_database_12.json", "time_exfiltrated": 574.7356433868408}, {"name": "data_database_33.json", "time_exfiltrated": 616.7356433868408}, {"name": "data_database_16.json", "time_exfiltrated": 674.7356433868408}, {"name": "data_database_2.json", "time_exfiltrated": 711.7356433868408}, {"name": "data_database_45.json", "time_exfiltrated": 754.7356433868408}, {"name": "data_database_25.json", "time_exfiltrated": 796.7356433868408}, {"name": "data_database_29.json", "time_exfiltrated": 838.7356433868408}, {"name": "data_database_41.json", "time_exfiltrated": 881.7356433868408}, {"name": "data_database_38.json", "time_exfiltrated": 918.7356433868408}, {"name": "data_database_34.json", "time_exfiltrated": 966.7356433868408}, {"name": "data_database_7.json", "time_exfiltrated": 1008.7356433868408}, {"name": "data_database_23.json", "time_exfiltrated": 1055.7356433868408}, {"name": "data_database_26.json", "time_exfiltrated": 1098.7356433868408}, {"name": "data_database_39.json", "time_exfiltrated": 1140.7356433868408}, {"name": "data_database_15.json", "time_exfiltrated": 1177.7356433868408}, {"name": "data_database_20.json", "time_exfiltrated": 1220.7356433868408}, {"name": "data_database_14.json", "time_exfiltrated": 1262.7356433868408}, {"name": "data_database_21.json", "time_exfiltrated": 1305.7356433868408}, {"name": "data_database_0.json", "time_exfiltrated": 1342.7356433868408}, {"name": "data_database_40.json", "time_exfiltrated": 1394.7356433868408}, {"name": "data_database_28.json", "time_exfiltrated": 1437.7356433868408}, {"name": "data_database_4.json", "time_exfiltrated": 1485.7356433868408}, {"name": "data_database_46.json", "time_exfiltrated": 1522.7356433868408}, {"name": "data_database_31.json", "time_exfiltrated": 1580.7356433868408}, {"name": "data_database_18.json", "time_exfiltrated": 1622.7356433868408}, {"name": "data_database_37.json", "time_exfiltrated": 1665.7356433868408}, {"name": "data_database_36.json", "time_exfiltrated": 1707.7356433868408}, {"name": "data_database_1.json", "time_exfiltrated": 1750.7356433868408}, {"name": "data_database_13.json", "time_exfiltrated": 1792.7356433868408}, {"name": "data_database_8.json", "time_exfiltrated": 1835.7356433868408}, {"name": "data_database_3.json", "time_exfiltrated": 1882.7356433868408}, {"name": "data_database_24.json", "time_exfiltrated": 1925.7356433868408}, {"name": "data_database_43.json", "time_exfiltrated": 1962.7356433868408}, {"name": "data_database_17.json", "time_exfiltrated": 2010.7356433868408}, {"name": "data_database_22.json", "time_exfiltrated": 2053.735643386841}, {"name": "data_database_11.json", "time_exfiltrated": 2100.735643386841}, {"name": "data_database_19.json", "time_exfiltrated": 2148.735643386841}, {"name": "data_database_35.json", "time_exfiltrated": 2190.735643386841}, {"name": "data_database_6.json", "time_exfiltrated": 2237.735643386841}], "hosts_infected": [{"name": "webserver-1", "time_infected": 92.58709955215454}, {"name": "webserver-0", "time_infected": 119.75967216491699}, {"name": "database-9", "time_infected": 151.9402244091034}, {"name": "database-27", "time_infected": 194.34517168998718}, {"name": "database-32", "time_infected": 231.72367119789124}, {"name": "database-47", "time_infected": 279.01300072669983}, {"name": "database-5", "time_infected": 321.310640335083}, {"name": "database-30", "time_infected": 373.603146314621}, {"name": "database-44", "time_infected": 410.9427056312561}, {"name": "database-42", "time_infected": 453.3264012336731}, {"name": "database-10", "time_infected": 495.67314076423645}, {"name": "database-12", "time_infected": 548.034351348877}, {"name": "database-33", "time_infected": 590.3960800170898}, {"name": "database-16", "time_infected": 627.733521938324}, {"name": "database-2", "time_infected": 685.1038291454315}, {"name": "database-45", "time_infected": 722.4431428909302}, {"name": "database-25", "time_infected": 764.8186638355255}, {"name": "database-29", "time_infected": 807.1664400100708}, {"name": "database-41", "time_infected": 849.6211793422699}, {"name": "database-38", "time_infected": 892.1556227207184}, {"name": "database-34", "time_infected": 929.4983108043671}, {"name": "database-7", "time_infected": 976.8978407382965}, {"name": "database-23", "time_infected": 1024.2323865890503}, {"name": "database-26", "time_infected": 1066.591936826706}, {"name": "database-39", "time_infected": 1109.039964914322}, {"name": "database-15", "time_infected": 1151.365449666977}, {"name": "database-20", "time_infected": 1188.7405948638916}, {"name": "database-14", "time_infected": 1231.2239468097687}, {"name": "database-21", "time_infected": 1273.536063671112}, {"name": "database-0", "time_infected": 1315.9721467494965}, {"name": "database-40", "time_infected": 1358.3095417022705}, {"name": "database-28", "time_infected": 1405.7661907672882}, {"name": "database-4", "time_infected": 1448.3615472316742}, {"name": "database-46", "time_infected": 1496.0791618824005}, {"name": "database-31", "time_infected": 1538.4432306289673}, {"name": "database-18", "time_infected": 1591.1195471286774}, {"name": "database-37", "time_infected": 1633.7136952877045}, {"name": "database-36", "time_infected": 1676.0742919445038}, {"name": "database-1", "time_infected": 1718.5079646110535}, {"name": "database-13", "time_infected": 1766.0564060211182}, {"name": "database-8", "time_infected": 1808.8098051548004}, {"name": "database-3", "time_infected": 1851.1964728832245}, {"name": "database-24", "time_infected": 1893.5608944892883}, {"name": "database-43", "time_infected": 1936.3152272701263}, {"name": "database-17", "time_infected": 1978.6828520298004}, {"name": "database-22", "time_infected": 2021.4822297096252}, {"name": "database-11", "time_infected": 2063.8526380062103}, {"name": "database-19", "time_infected": 2116.433482170105}, {"name": "database-35", "time_infected": 2163.836959838867}, {"name": "database-6", "time_infected": 2206.253993988037}], "operation_id": "2024-11-08_13-42-20", "defender_action_counts": {"shutdown_server": 0, "start_honey_service": 0, "deploy_decoy": 0, "restore_server": 0, "AddHoneyCredentials": 0}}