{"scenario": {"name": "EquifaxBaseline_WaitAndStop", "defender": {"telemetry": "SimpleTelemetryAnalysis", "strategy": "WaitAndStop", "capabilities": {"DeployDecoy": 2, "HoneyService": 0, "RestoreServer": -1, "HoneyCredentials": 4}}, "attacker": {"name": "RandomAttacker"}, "deployment_instance": {"name": "EquifaxInstance"}}, "experiment_time": 1098.6736381053925, "execution_time": 859.2082424163818, "setup_time": 239.46539568901062, "flags_captured": [], "data_exfiltrated": [{"name": "data2.json", "time_exfiltrated": 495.83457231521606}], "hosts_infected": ["attacker", "webserver-c", "webserver-a", "webserver-b", "employee-a", "employee-b", "database-b", "database-a", "decoy-1"], "operation_id": "e6cd28ce-5b54-482a-ab43-7a29d05d7ee8"}