{"scenario": {"name": "bfs_reactiveLayered_d10_h50", "defender": {"telemetry": "SimpleTelemetryAnalysis", "strategy": "ReactiveLayered", "capabilities": {"DeployDecoy": 10, "HoneyService": 0, "RestoreServer": -1, "HoneyCredentials": 50}}, "attacker": {"name": "BFSAttacker"}, "deployment_instance": {"name": "EquifaxLarge"}}, "experiment_time": 1853.7758693695068, "execution_time": 445.68702363967896, "setup_time": 1408.0888457298279, "flags_captured": [], "data_exfiltrated": [], "hosts_infected": ["attacker", "decoy-8", "decoy-5", "decoy-9", "decoy-4", "decoy-3", "decoy-1", "webserver-1", "webserver-0", "decoy-6", "decoy-2"], "operation_id": "7699fe77-6ba1-4be4-adac-d258fcbd759d", "defender_action_counts": {"shutdown_server": 0, "start_honey_service": 0, "deploy_decoy": 10, "restore_server": 8, "AddHoneyCredentials": 50}}