{"scenario": {"name": "Equifax", "defender": {"telemetry": "NoTelemetry", "strategy": "DoNothing", "capabilities": {"DeployDecoy": 0, "HoneyService": 0, "RestoreServer": 0}}, "attacker": {"name": "GreedyAttacker"}, "deployment_instance": {"name": "EquifaxInstance"}}, "experiment_time": 535.0964000225067, "execution_time": 484.5275013446808, "setup_time": 50.56889867782593, "flags_captured": [], "data_exfiltrated": [{"name": "data1.json", "time_exfiltrated": 290.5209515094757}, {"name": "data2.json", "time_exfiltrated": 355.5209515094757}], "hosts_infected": ["attacker", "webserver-b", "webserver-a", "webserver-c", "database-a", "employee-b", "employee-a", "database-b"], "operation_id": "3a719e34-663b-4e2d-80f1-4be4136e01e9"}