{"scenario": {"name": "dfs_d2_h4", "defender": {"telemetry": "NoTelemetry", "strategy": "StaticRandom", "capabilities": {"DeployDecoy": 2, "HoneyService": 0, "RestoreServer": 0, "HoneyCredentials": 4}}, "attacker": {"name": "GreedyAttacker"}, "deployment_instance": {"name": "EquifaxMedium"}}, "experiment_time": 2627.833055973053, "execution_time": 1686.5512528419495, "setup_time": 941.2818031311035, "flags_captured": [], "data_exfiltrated": [{"name": "data_database_0.json", "time_exfiltrated": 1082.6303803920746}, {"name": "data_database_3.json", "time_exfiltrated": 1118.6303803920746}, {"name": "data_database_4.json", "time_exfiltrated": 1163.6303803920746}, {"name": "data_database_1.json", "time_exfiltrated": 1238.6303803920746}, {"name": "data_database_2.json", "time_exfiltrated": 1273.6303803920746}], "hosts_infected": ["attacker", "webserver-5", "webserver-3", "webserver-8", "webserver-1", "webserver-4", "webserver-7", "webserver-0", "webserver-9", "webserver-2", "webserver-6", "decoy-1", "employee-2", "decoy-0", "employee-0", "employee-1", "database-0", "database-3", "database-4", "employee-4", "employee-3", "database-1", "database-2"], "operation_id": "a40089d4-8a04-47a2-a9c0-ad1212129c1e", "defender_action_counts": {"shutdown_server": 0, "start_honey_service": 0, "deploy_decoy": 2, "restore_server": 0, "AddHoneyCredentials": 20}}