{"scenario": {"name": "Equifax_HoneyCredentialDefender", "defender": {"telemetry": "NoTelemetry", "strategy": "StaticRandom", "capabilities": {"DeployDecoy": 2, "HoneyService": 2, "RestoreServer": 0, "HoneyCredentials": 1}}, "attacker": {"name": "EquifaxBaselineAttacker"}, "deployment_instance": {"name": "EquifaxInstance"}}, "experiment_time": 532.6465501785278, "execution_time": 264.6315131187439, "setup_time": 268.01503705978394, "flags_captured": [], "data_exfiltrated": [{"name": "data2.json", "time_exfiltrated": 175.05490159988403}, {"name": "data1.json", "time_exfiltrated": 261.05490159988403}], "hosts_infected": ["attacker", "webserver-c", "database-b", "employee-b", "employee-a", "decoy-1", "database-a"], "operation_id": "d15abf41-50a9-4ea0-9306-c782dda8316a"}